{
    "name": "myOrders",
    "vendor": "eComStyle.de",
    "id": "",
    "type": "oxid",
    "picture": "https://ecomstyle.de/out/pictures/generated/product/1/380_380_90/myo1(1).jpg",
    "price": 59.5,
    "license": "Commercial",
    "desc": {
        "de": "Erweiterte Bestellhistorie mit Zahlungs- und Versandinfos.",
        "en": ""
    },
    "tags": [],
    "versions": {
        "1.0.0": {
            "project": "https://ecomstyle.de/myorders.html",
            "url": "",
            "supported": [
                "6.0",
                "4.10",
                "4.9"
            ],
            "mapping": {
                "src": "",
                "dest": ""
            }
        }
    }
}